elementium/__init__.py
elementium/elements.py
elementium/exc.py
elementium/util.py
elementium/waiters.py
elementium/drivers/__init__.py
elementium/drivers/se.py
elementium-2.0.2.dist-info/LICENSE.txt
elementium-2.0.2.dist-info/METADATA
elementium-2.0.2.dist-info/WHEEL
elementium-2.0.2.dist-info/top_level.txt
elementium-2.0.2.dist-info/RECORD
